pyannotables/__init__.py
pyannotables/pyannotables.py
pyannotables/data/__init__.py
pyannotables/data/datafile_homo_sapiens-GRCh37-ensembl100-tx2gene.pkl.xz
pyannotables/data/datafile_homo_sapiens-GRCh37-ensembl100.pkl.xz
pyannotables/data/datafile_homo_sapiens-GRCh38-ensembl100-tx2gene.pkl.xz
pyannotables/data/datafile_homo_sapiens-GRCh38-ensembl100.pkl.xz
pyannotables/data/datafile_homo_sapiens-GRCh38-ensembl84-tx2gene.pkl.xz
pyannotables/data/datafile_homo_sapiens-GRCh38-ensembl84.pkl.xz
pyannotables/data/datafile_homo_sapiens-GRCh38-ensembl93-tx2gene.pkl.xz
pyannotables/data/datafile_homo_sapiens-GRCh38-ensembl93.pkl.xz
pyannotables/data/datafile_homology.pkl.xz
pyannotables/data/datafile_homology_grouped_geneentrez.pkl.xz
pyannotables/data/datafile_homology_grouped_genesymbol.pkl.xz
pyannotables/data/datafile_mus_musculus-GRCm38-ensembl100-tx2gene.pkl.xz
pyannotables/data/datafile_mus_musculus-GRCm38-ensembl100.pkl.xz
pyannotables-0.5.dist-info/AUTHORS.rst
pyannotables-0.5.dist-info/LICENSE
pyannotables-0.5.dist-info/METADATA
pyannotables-0.5.dist-info/WHEEL
pyannotables-0.5.dist-info/top_level.txt
pyannotables-0.5.dist-info/RECORD
