Metadata-Version: 2.1
Name: pyannotables
Version: 0.5
Summary: Python package for conversions between ENSEMBL IDs and gene names (annotables + pyensembl)
Home-page: https://github.com/gokceneraslan/pyannotables
Author: Gokcen Eraslan
Author-email: geraslan@broadinstitute.org
License: Apache Software License 2.0
Keywords: pyannotables
Platform: UNKNOWN
Classifier: Development Status :: 2 - Pre-Alpha
Classifier: Intended Audience :: Developers
Classifier: License :: OSI Approved :: Apache Software License
Classifier: Natural Language :: English
Classifier: Programming Language :: Python :: 3.5
Classifier: Programming Language :: Python :: 3.6
Classifier: Programming Language :: Python :: 3.7
Requires-Dist: pandas
